accelerator/OVERVIEW.txt
accelerator/__init__.py
accelerator/_dsutil.cpython-314-x86_64-linux-musl.so
accelerator/autoflush.py
accelerator/blob.py
accelerator/board.py
accelerator/build.py
accelerator/colourwrapper.py
accelerator/compat.py
accelerator/configfile.py
accelerator/control.py
accelerator/database.py
accelerator/dataset.py
accelerator/dependency.py
accelerator/deptree.py
accelerator/dispatch.py
accelerator/dsutil.py
accelerator/error.py
accelerator/extras.py
accelerator/g.py
accelerator/graph.py
accelerator/iowrapper.py
accelerator/job.py
accelerator/launch.py
accelerator/metadata.py
accelerator/methods.py
accelerator/mp.py
accelerator/runner.py
accelerator/server.py
accelerator/setupfile.py
accelerator/statmsg.py
accelerator/subjobs.py
accelerator/unixhttp.py
accelerator/urd.py
accelerator/version.txt
accelerator/web.py
accelerator/workarounds.py
accelerator/workspace.py
accelerator/board/dataset.tpl
accelerator/board/dircontents.tpl
accelerator/board/graph.js
accelerator/board/graph.tpl
accelerator/board/head.tpl
accelerator/board/job.tpl
accelerator/board/job_method_list.tpl
accelerator/board/last_error.tpl
accelerator/board/main.tpl
accelerator/board/method.tpl
accelerator/board/methods.tpl
accelerator/board/rendergraph.tpl
accelerator/board/script.js
accelerator/board/status.tpl
accelerator/board/style.css
accelerator/board/urd.tpl
accelerator/board/urditem.tpl
accelerator/board/urdlist.tpl
accelerator/board/workdir.tpl
accelerator/examples/__init__.py
accelerator/examples/a_dsexample_aggandmergedata.py
accelerator/examples/a_dsexample_appendcolumn.py
accelerator/examples/a_dsexample_createdataset.py
accelerator/examples/a_dsexample_iterateandmerge.py
accelerator/examples/a_dsexample_iteratechain.py
accelerator/examples/a_dsexample_multipledatasets.py
accelerator/examples/a_example_buildsubjob.py
accelerator/examples/a_example_dependextra.py
accelerator/examples/a_example_dummyjob.py
accelerator-2025.11.11.dist-info/METADATA
accelerator-2025.11.11.dist-info/WHEEL
accelerator-2025.11.11.dist-info/entry_points.txt
accelerator-2025.11.11.dist-info/top_level.txt
accelerator-2025.11.11.dist-info/RECORD
accelerator-2025.11.11.dist-info/licenses/LICENSE
