Metadata-Version: 2.1
Name: accelerator
Version: 2025.11.11
Summary: A tool for fast and reproducible processing of large amounts of data.
Home-page: https://exax.org/
Author: Carl Drougge
Author-email: bearded@longhaired.org
License: UNKNOWN
Project-URL: Source, https://github.com/exaxorg/accelerator
Project-URL: Documentation, https://exax.readthedocs.io/
Project-URL: Reference manual, https://berkeman.github.io/pdf/acc_manual.pdf
Platform: UNKNOWN
Classifier: Development Status :: 5 - Production/Stable
Classifier: Environment :: Console
Classifier: Intended Audience :: Developers
Classifier: Intended Audience :: Science/Research
Classifier: License :: OSI Approved :: Apache Software License
Classifier: Operating System :: POSIX
Classifier: Operating System :: POSIX :: BSD :: FreeBSD
Classifier: Operating System :: POSIX :: Linux
Classifier: Programming Language :: Python :: 2
Classifier: Programming Language :: Python :: 2.7
Classifier: Programming Language :: Python :: 3
Classifier: Programming Language :: Python :: 3.5
Classifier: Programming Language :: Python :: 3.6
Classifier: Programming Language :: Python :: 3.7
Classifier: Programming Language :: Python :: 3.8
Classifier: Programming Language :: Python :: 3.9
Classifier: Programming Language :: Python :: 3.10
Classifier: Programming Language :: Python :: 3.11
Classifier: Programming Language :: Python :: 3.12
Classifier: Programming Language :: Python :: 3.13
Classifier: Programming Language :: Python :: 3.14
Classifier: Programming Language :: Python :: Implementation :: CPython
Classifier: Programming Language :: C
Requires-Python: >=2.7, !=3.0.*, !=3.1.*, !=3.2.*, !=3.3.*, !=3.4.*, <4
License-File: LICENSE
Requires-Dist: setproctitle (>=1.1.8)
Requires-Dist: waitress (>=1.0)
Requires-Dist: configparser (<5.0,>=3.5.0) ; python_version < "3"
Requires-Dist: monotonic (>=1.0) ; python_version < "3"
Requires-Dist: selectors2 (>=2.0) ; python_version < "3"
Requires-Dist: pathlib (>=1.0) ; python_version < "3"
Requires-Dist: bottle (<0.13,>=0.12.7) ; python_version < "3.10"
Requires-Dist: bottle (<0.14,>=0.13) ; python_version >= "3.10"
